setup.py
sumoftwonumbers/__init__.py
sumoftwonumbers/sumoftwonumbers.py
sumoftwonumbers.egg-info/PKG-INFO
sumoftwonumbers.egg-info/SOURCES.txt
sumoftwonumbers.egg-info/dependency_links.txt
sumoftwonumbers.egg-info/not-zip-safe
sumoftwonumbers.egg-info/top_level.txt