Metadata-Version: 2.1
Name: sumoftwonumbers
Version: 0.1
Summary: It will add given two Numbers of Your Choice
Author: HariSrujan Reddy C
